skill_randomness/__init__.py
skill_randomness/coin-flip.wav
skill_randomness/die-roll.wav
skill_randomness/magic.mp3
skill_randomness/version.py
skill_randomness/locale/en-us/dialog/choice-result.dialog
skill_randomness/locale/en-us/dialog/coin-result.dialog
skill_randomness/locale/en-us/dialog/die-result.dialog
skill_randomness/locale/en-us/dialog/first-choice.dialog
skill_randomness/locale/en-us/dialog/fortune-query.dialog
skill_randomness/locale/en-us/dialog/fortune-result.dialog
skill_randomness/locale/en-us/dialog/multiple-die-result.dialog
skill_randomness/locale/en-us/dialog/number-range-not-specified.dialog
skill_randomness/locale/en-us/dialog/number-result.dialog
skill_randomness/locale/en-us/dialog/over-dice-limit.dialog
skill_randomness/locale/en-us/dialog/second-choice.dialog
skill_randomness/locale/en-us/intents/flip-a-coin.intent
skill_randomness/locale/en-us/intents/fortune-teller.intent
skill_randomness/locale/en-us/intents/make-a-choice.intent
skill_randomness/locale/en-us/intents/pick-a-number.intent
skill_randomness/locale/en-us/intents/roll-multiple-dice.intent
skill_randomness/locale/en-us/intents/roll-single-die.intent
skill_randomness-0.0.2a1.dist-info/METADATA
skill_randomness-0.0.2a1.dist-info/WHEEL
skill_randomness-0.0.2a1.dist-info/entry_points.txt
skill_randomness-0.0.2a1.dist-info/top_level.txt
skill_randomness-0.0.2a1.dist-info/RECORD
