Metadata-Version: 2.1
Name: skill-randomness
Version: 0.0.2a1
Summary: UNKNOWN
Home-page: https://github.com/mikejgray/skill-randomness
Author: Mike Gray
Author-email: mike@graywind.org
License: MIT
Keywords: ovos skill voice assistant
Platform: UNKNOWN
Requires-Dist: ovos-utils
Requires-Dist: ovos-workshop
Requires-Dist: ovos-lingua-franca
Requires-Dist: icepool
Provides-Extra: test
Requires-Dist: pytest; extra == "test"
Requires-Dist: ovos-plugin-manager; extra == "test"
Requires-Dist: padacioso; extra == "test"
